cosmosdb/__init__.py
cosmosdb/db.py
flixtube_common_test1-0.0.1.dist-info/METADATA
flixtube_common_test1-0.0.1.dist-info/WHEEL
flixtube_common_test1-0.0.1.dist-info/top_level.txt
flixtube_common_test1-0.0.1.dist-info/RECORD
